PyElectroSim/__init__.py
PyElectroSim/cargas.py
PyElectroSim/conf.py
PyElectroSim/simulador.py
PyElectroSim/sistema.py
PyElectroSim-0.0.121.dist-info/LICENSE
PyElectroSim-0.0.121.dist-info/METADATA
PyElectroSim-0.0.121.dist-info/WHEEL
PyElectroSim-0.0.121.dist-info/top_level.txt
PyElectroSim-0.0.121.dist-info/RECORD
