Metadata-Version: 2.1
Name: PyElectroSim
Version: 0.0.121
Summary: PyElectroSim é uma biblioteca para simulação da trajetória de cargas elétricas em um sistema de coordenadas cartesianas.
Author: Robson-tech
Author-email: robson.junior@ufpi.edu.br
License: MIT
License-File: LICENSE
Requires-Dist: pygame
